tap_awin/__init__.py
tap_awin/schemas/merchants.json
tap_awin/schemas/transactions.json
tap_awin-0.0.4.dist-info/DESCRIPTION.rst
tap_awin-0.0.4.dist-info/METADATA
tap_awin-0.0.4.dist-info/RECORD
tap_awin-0.0.4.dist-info/WHEEL
tap_awin-0.0.4.dist-info/entry_points.txt
tap_awin-0.0.4.dist-info/metadata.json
tap_awin-0.0.4.dist-info/top_level.txt
