Metadata-Version: 2.0
Name: tap-awin
Version: 0.0.4
Summary: Singer.io tap for extracting data from the Affiliate Window API
Home-page: https://github.com/onedox/tap-awin
Author: Onedox
Author-email: UNKNOWN
License: UNKNOWN
Platform: UNKNOWN
Classifier: Programming Language :: Python :: 3 :: Only
Requires-Dist: zeep (>=1.4.1)
Requires-Dist: singer-python (>=3.6.3)
Requires-Dist: tzlocal (>=1.3)
